dataeng_sdk/__init__.py
dataeng_sdk/common_tool.py
dataeng_sdk/common_tool_test.py
dataeng_sdk/const.py
dataeng_sdk/operator_base.py
dataeng_sdk/operator_base_test.py
dataeng_sdk/operator_mock_test.py
dataeng_sdk-0.1.dist-info/LICENSE
dataeng_sdk-0.1.dist-info/METADATA
dataeng_sdk-0.1.dist-info/WHEEL
dataeng_sdk-0.1.dist-info/entry_points.txt
dataeng_sdk-0.1.dist-info/top_level.txt
dataeng_sdk-0.1.dist-info/RECORD
