Metadata-Version: 2.1
Name: dataeng-sdk
Version: 0.1
Summary: dataengine 平台算子接入sdk
Home-page: https://console.cloud.baidu-int.com/devops/icode/repos/baidu/dataeng/dataeng-sdk/tree/master
Author: qiguoning01
Author-email: qiguoning01@baidu.com
License: UNKNOWN
Platform: UNKNOWN
License-File: LICENSE
Requires-Dist: requests
